testpkg3_ftcao/__init__.py
testpkg3_ftcao/testpkg3_ftcao.py
testpkg3_ftcao-0.1.0.dist-info/LICENSE
testpkg3_ftcao-0.1.0.dist-info/METADATA
testpkg3_ftcao-0.1.0.dist-info/WHEEL
testpkg3_ftcao-0.1.0.dist-info/RECORD
